pytpp/__init__.py
pytpp/__main__.py
pytpp/tpp_gui.py
pytpp/tpp_tools.py
pytransit/README.md
pytransit/__init__.py
pytransit/__init__.pyc
pytransit/__main__.py
pytransit/__main__.pyc
pytransit/globals.py
pytransit/transit_cli.py
pytransit/transit_gui.py
pytransit/components/DejaVuSans.ttf
pytransit/components/annotation_area.py
pytransit/components/draw_trash.py
pytransit/components/file_display.py
pytransit/components/icon.py
pytransit/components/images.py
pytransit/components/menu.py
pytransit/components/panel_helpers.py
pytransit/components/parameter_panel.py
pytransit/components/pop_up.py
pytransit/components/qc_display.py
pytransit/components/results_area.py
pytransit/components/samples_area.py
pytransit/components/spreadsheet.py
pytransit/components/trash.py
pytransit/components/view_trash.py
pytransit/components/generic/box.py
pytransit/components/generic/button.py
pytransit/components/generic/checkbox.wip.py
pytransit/components/generic/drag_and_drop.wip.py
pytransit/components/generic/frame.py
pytransit/components/generic/table.py
pytransit/components/generic/text.py
pytransit/components/generic/window_manager.py
pytransit/data/COG_20_roles.txt
pytransit/data/GO_associated_Rvs-3-11-18.txt
pytransit/data/GO_associated_Rvs.csv
pytransit/data/GO_associated_Rvs.txt
pytransit/data/GO_term_names.dat
pytransit/data/GO_terms_for_each_Rv.obo-3-11-18.txt
pytransit/data/H37Rv.sanger_associated_RVS.csv
pytransit/data/H37Rv_COG_20_roles.txt
pytransit/data/H37Rv_GO_terms.txt
pytransit/data/H37Rv_KEGG_roles.txt
pytransit/data/H37Rv_sanger_roles.dat
pytransit/data/KEGG_roles.txt
pytransit/data/Mycobacterium_tuberculosis_H37Rv_COG_20_roles.associations.txt
pytransit/data/NC_003062.2.gff3
pytransit/data/NC_003062.2.prot_table
pytransit/data/README.md
pytransit/data/cog-20.org.csv
pytransit/data/comwig.tsv
pytransit/data/iron.combined_wig.txt
pytransit/data/iron_metadata.txt
pytransit/data/recent_export.comwig.gff.tsv
pytransit/data/recent_export.comwig.tsv
transit2-1.1.9.dist-info/licenses/LICENSE.md
transit2-1.1.9.dist-info/METADATA
transit2-1.1.9.dist-info/WHEEL
transit2-1.1.9.dist-info/entry_points.txt
transit2-1.1.9.dist-info/top_level.txt
transit2-1.1.9.dist-info/RECORD
