Metadata-Version: 2.4
Name: transit2
Version: 1.1.9
Summary: TRANSIT2 is a tool for the analysis of Tn-Seq data. It provides an easy to use graphical interface and access to three different analysis methods that allow the user to determine essentiality in a single condition as well as between conditions.
Home-page: https://orca1.tamu.edu/essentiality/transit/index.html
Download-URL: https://github.com/ioerger/transit2
Author: Thomas R. Ioerger
Author-email: ioerger@cs.tamu.edu
License: GNU GPL
Keywords: tnseq,analysis,biology,genome
Classifier: Development Status :: 5 - Production/Stable
Classifier: Programming Language :: Python
Classifier: Programming Language :: Python :: 3
Classifier: Intended Audience :: Science/Research
Classifier: License :: OSI Approved :: GNU General Public License v3 (GPLv3)
Classifier: Operating System :: OS Independent
Classifier: Topic :: Scientific/Engineering :: Bio-Informatics
Requires-Python: >=3.6
License-File: LICENSE.md
Requires-Dist: setuptools
Requires-Dist: wxPython
Requires-Dist: attrdict~=2.0
Requires-Dist: numpy~=1.16
Requires-Dist: scipy~=1.2
Requires-Dist: matplotlib~=3.0
Requires-Dist: scikit-learn~=1.1
Requires-Dist: statsmodels~=0.9
Requires-Dist: pandas~=2.0
Requires-Dist: seaborn>=0.11.2
Requires-Dist: ez-yaml~=2.0
Requires-Dist: super-hash~=1.2
Requires-Dist: mne~=1.5
Dynamic: author
Dynamic: author-email
Dynamic: classifier
Dynamic: description
Dynamic: description-content-type
Dynamic: download-url
Dynamic: home-page
Dynamic: keywords
Dynamic: license
Dynamic: license-file
Dynamic: requires-dist
Dynamic: requires-python
Dynamic: summary
